{"pageContext":{"slug":"/bicicultura-pwa/","previous":{"excerpt":"Context VTEX is a global SaaS technology company focused on ecommerce solutions that have a daily impact on the work of thousands of people…","fields":{"slug":"/vtex-home/"},"frontmatter":{"date":"2018-03","date2":"2018-10","title":"VTEX Admin Home","description":"A new home for the an e-commerce platform admin, setting the ground for a new generation of Admin UIs.","tags":["UI/UX","work"],"cover":{"publicURL":"/static/photo_cropped-567d6ed72ad0f68131cd64bc5aad34ad.jpg"}}},"next":null}}